pydvp/__init__.py
pydvp/core.py
pydvp/tcp_client.py
pydvp-4.2.0.dist-info/licenses/LICENSE
pydvp-4.2.0.dist-info/METADATA
pydvp-4.2.0.dist-info/WHEEL
pydvp-4.2.0.dist-info/top_level.txt
pydvp-4.2.0.dist-info/RECORD
