Metadata-Version: 2.4
Name: PyDVP
Version: 4.2.0
Summary: A DEXON DIVIP Python library
Home-page: https://dexonsystems.com/contact
Author: Dexon Systems Ltd.
Author-email: sales@dexonsystems.com
Classifier: Programming Language :: Python :: 3
Classifier: License :: OSI Approved :: MIT License
Classifier: Operating System :: OS Independent
Requires-Python: >=3.6
License-File: LICENSE
Dynamic: author
Dynamic: author-email
Dynamic: classifier
Dynamic: description
Dynamic: description-content-type
Dynamic: home-page
Dynamic: license-file
Dynamic: requires-python
Dynamic: summary
